CHANGES.txt
LICENSE.txt
MANIFEST.in
README.rst
requirements.txt
setup.py
canopener/__init__.py
canopener/core.py
canopener/s3file.py
canopener.egg-info/PKG-INFO
canopener.egg-info/SOURCES.txt
canopener.egg-info/dependency_links.txt
canopener.egg-info/requires.txt
canopener.egg-info/top_level.txt