Metadata-Version: 1.0
Name: canopener
Version: 0.1.6
Summary: Python convenience function for opening compressed URLs and files.
Home-page: https://github.com/selassid/canopener
Author: David Selassie
Author-email: selassid@gmail.com
License: Copyright (c) 2012-2014, David Selassie
